rich_tables/__init__.py
rich_tables/calendar.py
rich_tables/diff.py
rich_tables/fields.py
rich_tables/generic.py
rich_tables/github.py
rich_tables/log_handler.py
rich_tables/music.py
rich_tables/py.typed
rich_tables/table.py
rich_tables/task.py
rich_tables/utils.py
rich_tables-0.8.0.dist-info/LICENSE
rich_tables-0.8.0.dist-info/METADATA
rich_tables-0.8.0.dist-info/WHEEL
rich_tables-0.8.0.dist-info/entry_points.txt
rich_tables-0.8.0.dist-info/RECORD
