Metadata-Version: 2.3
Name: rich-tables
Version: 0.8.0
Summary: Ready-made rich tables for various purposes
License: MIT
Keywords: json,pretty,rich,console,terminal
Author: Šarūnas Nejus
Author-email: snejus@pm.me
Requires-Python: >=3.9,<4
Classifier: Development Status :: 1 - Planning
Classifier: Environment :: Console
Classifier: Intended Audience :: End Users/Desktop
Classifier: Intended Audience :: System Administrators
Classifier: License :: OSI Approved :: MIT License
Classifier: Operating System :: OS Independent
Classifier: Programming Language :: Python :: 3
Classifier: Programming Language :: Python :: 3.9
Classifier: Programming Language :: Python :: 3.10
Classifier: Programming Language :: Python :: 3.11
Classifier: Programming Language :: Python :: 3.12
Classifier: Programming Language :: Python :: 3.13
Classifier: Topic :: Utilities
Provides-Extra: hue
Requires-Dist: coloraide (>=4.1)
Requires-Dist: humanize (>=4.11.0)
Requires-Dist: multimethod (<2)
Requires-Dist: platformdirs (>=4.2.0)
Requires-Dist: rgbxy (>=0.5) ; extra == "hue"
Requires-Dist: rich (>=12.3.0)
Requires-Dist: sqlparse (>=0.4.4)
Requires-Dist: typing-extensions (>=4.7.1)
Project-URL: Homepage, https://github.com/snejus/rich-tables
Project-URL: Repository, https://github.com/snejus/rich-tables
